odoo/addons/l10n_br_nfe_spec/README.rst
odoo/addons/l10n_br_nfe_spec/__init__.py
odoo/addons/l10n_br_nfe_spec/__manifest__.py
odoo/addons/l10n_br_nfe_spec/i18n/l10n_br_nfe_spec.pot
odoo/addons/l10n_br_nfe_spec/i18n/pt_BR.po
odoo/addons/l10n_br_nfe_spec/models/__init__.py
odoo/addons/l10n_br_nfe_spec/models/spec_mixin.py
odoo/addons/l10n_br_nfe_spec/models/v4_0/__init__.py
odoo/addons/l10n_br_nfe_spec/models/v4_0/dfe_tipos_basicos_v1_00.py
odoo/addons/l10n_br_nfe_spec/models/v4_0/leiaute_cons_sit_nfe_v4_00.py
odoo/addons/l10n_br_nfe_spec/models/v4_0/leiaute_nfe_v4_00.py
odoo/addons/l10n_br_nfe_spec/models/v4_0/tipos_basico_v4_00.py
odoo/addons/l10n_br_nfe_spec/readme/CONFIGURE.md
odoo/addons/l10n_br_nfe_spec/readme/CONTRIBUTORS.md
odoo/addons/l10n_br_nfe_spec/readme/DESCRIPTION.md
odoo/addons/l10n_br_nfe_spec/readme/INSTALL.md
odoo/addons/l10n_br_nfe_spec/readme/ROADMAP.md
odoo/addons/l10n_br_nfe_spec/readme/USAGE.md
odoo/addons/l10n_br_nfe_spec/static/description/icon.png
odoo/addons/l10n_br_nfe_spec/static/description/index.html
odoo/addons/l10n_br_nfe_spec/tests/__init__.py
odoo/addons/l10n_br_nfe_spec/tests/test_nfe_import.py
odoo_addon_l10n_br_nfe_spec-18.0.2.0.0.1.dist-info/METADATA
odoo_addon_l10n_br_nfe_spec-18.0.2.0.0.1.dist-info/WHEEL
odoo_addon_l10n_br_nfe_spec-18.0.2.0.0.1.dist-info/top_level.txt
odoo_addon_l10n_br_nfe_spec-18.0.2.0.0.1.dist-info/RECORD
